tomodo/__init__.py
tomodo/cli/__init__.py
tomodo/cli/ops_manager.py
tomodo/cli/provision.py
tomodo/cli/tags.py
tomodo/cmd.py
tomodo/common/__init__.py
tomodo/common/cleaner.py
tomodo/common/config.py
tomodo/common/errors.py
tomodo/common/models.py
tomodo/common/om_provisioner.py
tomodo/common/om_server_provisioner.py
tomodo/common/provisioner.py
tomodo/common/reader.py
tomodo/common/starter.py
tomodo/common/tag_manager.py
tomodo/common/util.py
tomodo/functional.py
tomodo-1.4.3.dist-info/LICENSE
tomodo-1.4.3.dist-info/METADATA
tomodo-1.4.3.dist-info/WHEEL
tomodo-1.4.3.dist-info/entry_points.txt
tomodo-1.4.3.dist-info/RECORD
