Metadata-Version: 2.1
Name: tomodo
Version: 1.4.3
Summary: A CLI for managing MongoDB deployments on Docker
Home-page: https://tomodo.dev
License: MIT
Keywords: mongodb,docker,upgrade,python,cli
Author: Yuval Herziger
Author-email: yuvalhrz@gmail.com
Requires-Python: >=3.8,<3.13
Classifier: License :: OSI Approved :: MIT License
Classifier: Programming Language :: Python :: 3
Classifier: Programming Language :: Python :: 3.8
Classifier: Programming Language :: Python :: 3.9
Classifier: Programming Language :: Python :: 3.10
Classifier: Programming Language :: Python :: 3.11
Requires-Dist: docker (>=7.0.0,<8.0.0)
Requires-Dist: pymongo (>=4.8.0,<5.0.0)
Requires-Dist: requests (>=2.31.0,<3.0.0)
Requires-Dist: ruamel-yaml (>=0.17.32,<0.18.0)
Requires-Dist: typer[all] (>=0.9.0,<0.10.0)
Requires-Dist: unique-names-generator (>=1.0.2,<2.0.0)
Project-URL: Repository, https://github.com/yuvalherziger/tomodo
